{
  "project_info": {
    "project_number": "460750150714",
    "firebase_url": "https://mobilecoffloading-bd90b.firebaseio.com",
    "project_id": "mobilecoffloading-bd90b",
    "storage_bucket": "mobilecoffloading-bd90b.appspot.com"
  },
  "client": [
    {
      "client_info": {
        "mobilesdk_app_id": "1:460750150714:android:22efab8e9caf73f7",
        "android_client_info": {
          "package_name": "t2.mcc.iic3380.puc.edu.mcc_t2"
        }
      },
      "oauth_client": [
        {
          "client_id": "460750150714-k31rfeorupc4j21v5g7pcce061r9sa4l.apps.googleusercontent.com",
          "client_type": 3
        }
      ],
      "api_key": [
        {
          "current_key": "AIzaSyCd2o1TlGKpCE5aRclqtfmIgf0gWLpJrpI"
        }
      ],
      "services": {
        "analytics_service": {
          "status": 1
        },
        "appinvite_service": {
          "status": 1,
          "other_platform_oauth_client": []
        },
        "ads_service": {
          "status": 2
        }
      }
    }
  ],
  "configuration_version": "1"
}